certificates/__main__.py
certificates/certificates.py
certificates-2.0.0.dist-info/LICENSE
certificates-2.0.0.dist-info/METADATA
certificates-2.0.0.dist-info/WHEEL
certificates-2.0.0.dist-info/entry_points.txt
certificates-2.0.0.dist-info/RECORD
