Metadata-Version: 2.1
Name: certificates
Version: 2.0.0
Summary: Generate event certificates easily.
Home-page: https://github.com/cassiobotaro/certificates
License: Apache-2.0
Author: cassiobotaro
Author-email: cassiobotaro@gmail.com
Requires-Python: >=3.10,<4.0
Classifier: License :: OSI Approved :: Apache Software License
Classifier: Programming Language :: Python :: 3
Classifier: Programming Language :: Python :: 3.10
Classifier: Programming Language :: Python :: 3.11
